dungngo_mcp_obsidian-0.2.2.dist-info/licenses/LICENSE
mcp_obsidian/__init__.py
mcp_obsidian/obsidian.py
mcp_obsidian/server.py
mcp_obsidian/tools.py
dungngo_mcp_obsidian-0.2.2.dist-info/METADATA
dungngo_mcp_obsidian-0.2.2.dist-info/WHEEL
dungngo_mcp_obsidian-0.2.2.dist-info/entry_points.txt
dungngo_mcp_obsidian-0.2.2.dist-info/top_level.txt
dungngo_mcp_obsidian-0.2.2.dist-info/RECORD
