Metadata-Version: 2.4
Name: dungngo-mcp-obsidian
Version: 0.2.2
Summary: MCP server to work with Obsidian via the remote REST plugin (republished for testing)
Author-email: dungngo <test@dungngo.dev>
Requires-Python: >=3.11
License-File: LICENSE
Requires-Dist: mcp>=1.1.0
Requires-Dist: python-dotenv>=1.0.1
Requires-Dist: requests>=2.32.3
Dynamic: license-file
